doc2sdo/__init__.py
doc2sdo/defaults.py
doc2sdo/doc2sdo.py
doc2sdo/documents/__init__.py
doc2sdo/documents/document.py
doc2sdo/documents/pdf_document.py
doc2sdo/documents/text_document.py
doc2sdo/llm_spacy_model.py
doc2sdo/main.py
doc2sdo/named_entity_recognizer.py
doc2sdo/namespaces/__init__.py
doc2sdo/namespaces/doc2sdo.py
doc2sdo/py.typed
doc2sdo/spacy_model.py
doc2sdo/types/__init__.py
doc2sdo/types/creative_work.py
doc2sdo/types/organization.py
doc2sdo/types/person.py
doc2sdo/types/place.py
doc2sdo/types/thing.py
doc2sdo-1.0.0.dist-info/LICENSE
doc2sdo-1.0.0.dist-info/METADATA
doc2sdo-1.0.0.dist-info/WHEEL
doc2sdo-1.0.0.dist-info/entry_points.txt
doc2sdo-1.0.0.dist-info/RECORD
