Metadata-Version: 2.1
Name: doc2sdo
Version: 1.0.0
Summary: Extract entities from text documents and transform them to schema.org resources
License: GPLv3
Author: Minor Gordon
Author-email: minorg@server.fake
Requires-Python: >=3.10,<3.12
Classifier: License :: Other/Proprietary License
Classifier: Programming Language :: Python :: 3
Classifier: Programming Language :: Python :: 3.10
Classifier: Programming Language :: Python :: 3.11
Requires-Dist: nltk (>=3.8.1,<4.0.0)
Requires-Dist: pdfminer-six (>=20231228,<20231229)
Requires-Dist: pdftotext (>=2.2.2,<3.0.0)
Requires-Dist: python-dateutil (>=2.8.2,<3.0.0)
Requires-Dist: rdflib (>=7.0.0,<8.0.0)
Requires-Dist: spacy (>=3.7.2,<4.0.0)
Requires-Dist: spacy-llm (>=0.6.4,<0.7.0)
Requires-Dist: stringcase (>=1.2.0,<2.0.0)
Requires-Dist: tiktoken (>=0.5.2,<0.6.0)
Requires-Dist: typer (>=0.9.0,<0.10.0)
Requires-Dist: types-python-dateutil (>=2.8.19.20240106,<3.0.0.0)
